betterud/__init__.py
betterud/parser.py
betterud-1.0.2.dist-info/METADATA
betterud-1.0.2.dist-info/WHEEL
betterud-1.0.2.dist-info/licenses/LICENSE
betterud-1.0.2.dist-info/RECORD
