Metadata-Version: 2.3
Name: betterUD
Version: 1.0.2
Summary: A better solution to parse definitions from Urban Dictionary for python
Project-URL: Git, https://github.com/k0fNet/betterud
Author-email: k0fNet <k0fNet@protonmail.com>
License-File: LICENSE
Classifier: License :: OSI Approved :: MIT License
Classifier: Operating System :: OS Independent
Classifier: Programming Language :: Python :: 3.7
Classifier: Programming Language :: Python :: 3.8
Classifier: Programming Language :: Python :: 3.9
Classifier: Programming Language :: Python :: 3.10
Classifier: Programming Language :: Python :: 3.11
Classifier: Programming Language :: Python :: 3.12
Requires-Python: >=3.7.0
